color_temp/__init__.py
color_temp/color.py
color_temp-0.1.0.dist-info/DESCRIPTION.rst
color_temp-0.1.0.dist-info/METADATA
color_temp-0.1.0.dist-info/RECORD
color_temp-0.1.0.dist-info/WHEEL
color_temp-0.1.0.dist-info/metadata.json
color_temp-0.1.0.dist-info/top_level.txt
color_temp-0.1.0.dist-info/zip-safe
tests/__init__.py
tests/test_color.py
