Metadata-Version: 2.0
Name: color-temp
Version: 0.1.0
Summary: Convert color from RGB to Kelvin and back
Home-page: https://github.com/narfman0/color-temp
Author: Jon Robison
Author-email: narfman0@gmail.com
License: LICENSE
Keywords: color temperature
Platform: UNKNOWN
Classifier: Development Status :: 4 - Beta
Classifier: License :: OSI Approved :: GNU General Public License v3 (GPLv3)
Classifier: Operating System :: OS Independent
Classifier: Programming Language :: Python
Classifier: Topic :: Software Development :: Libraries :: Python Modules
Requires-Dist: colour-science
Requires-Dist: numpy
